robo_cop/__init__.py
robo_cop/__main__.py
robo_cop/row.py
robo_cop/watchdog.py
tests/__init__.py
tests/spec_hello_world.py
robo_cop-0.0.2.dist-info/LICENSE
robo_cop-0.0.2.dist-info/METADATA
robo_cop-0.0.2.dist-info/WHEEL
robo_cop-0.0.2.dist-info/entry_points.txt
robo_cop-0.0.2.dist-info/top_level.txt
robo_cop-0.0.2.dist-info/RECORD
